Metadata-Version: 1.1
Name: jsonmatch
Version: 0.3
Summary: A flexible framework for testing JSON dicts against schemas.
Home-page: https://github.com/percolate/jsonmatch
Author: jamesob, bcen
Author-email: bocai@percolate.com
License: see LICENCE.txt
Platform: UNKNOWN
Classifier: Intended Audience :: Developers
Classifier: License :: OSI Approved :: BSD License
Classifier: Operating System :: OS Independent
Classifier: Programming Language :: Python :: 2.7
Classifier: Topic :: Software Development :: Libraries :: Python Modules
Classifier: Topic :: Software Development :: Testing
